pyconsole_codes/__init__.py
pyconsole_codes/decode.py
pyconsole_codes/encode.py
pyconsole_codes/types/__init__.py
pyconsole_codes/types/csi.py
pyconsole_codes/types/esc.py
pyconsole_codes-0.0.2.dist-info/LICENSE
pyconsole_codes-0.0.2.dist-info/METADATA
pyconsole_codes-0.0.2.dist-info/WHEEL
pyconsole_codes-0.0.2.dist-info/top_level.txt
pyconsole_codes-0.0.2.dist-info/RECORD
