Metadata-Version: 2.1
Name: pyconsole_codes
Version: 0.0.2
Summary: 终端彩色字解析
Home-page: https://github.com/Inotart/pyconsole_codes
Author: 我不是art
Author-email: 121980156@qq.com
Classifier: Programming Language :: Python :: 3
Classifier: License :: OSI Approved :: MIT License
Classifier: Operating System :: OS Independent
Requires-Python: >=3.10
License-File: LICENSE
